pubmed_mcp_server/__init__.py
pubmed_mcp_server/main.py
pubmed_mcp_server/pubmed.py
pubmed_mcp_server-0.1.2.dist-info/METADATA
pubmed_mcp_server-0.1.2.dist-info/WHEEL
pubmed_mcp_server-0.1.2.dist-info/entry_points.txt
pubmed_mcp_server-0.1.2.dist-info/RECORD
