Metadata-Version: 2.3
Name: pubmed_mcp_server
Version: 0.1.2
Summary: 
Author: zelin
Author-email: zelinjiang@cuhk.edu.hk
Requires-Python: >=3.10
Classifier: Programming Language :: Python :: 3
Classifier: Programming Language :: Python :: 3.10
Classifier: Programming Language :: Python :: 3.11
Classifier: Programming Language :: Python :: 3.12
Classifier: Programming Language :: Python :: 3.13
Requires-Dist: mcp (>=1.0.0)
Requires-Dist: python-dotenv (>=1.0.0)
Requires-Dist: requests (>=2.31.0)
Requires-Dist: uvicorn (>=0.32.1)
